{
    "nav_opt_unAuth" : [
        {
            "name" : "Home",
            "route" : "/home"
        },
        {
            "name" : "Courses",
            "route" : "/courses",
            "isSubMenu" : true,
            "sub_options" : [{
                    "name" : "One",
                    "route" : "/one"
                },
                {
                    "name" : "Two",
                "route" : "/two"
                },
                {
                    "name" : "Three",
                    "route" : "/three"
                }        
            ]
        },
        {
            "name" : "Tutors",
            "route" : "/tutors",
            "isSubMenu" : true,
            "sub_options" :[{
                    "name" : "One",
                    "route" : "/one"
                },
                {
                    "name" : "Two",
                "route" : "/two"
                },
                {
                    "name" : "Three",
                    "route" : "/three"
                }        
            ]
        },
        {
            "name" : "Resources",
            "route" : "/resources",
            "isSubMenu" : true,
            "sub_options" : [{
                    "name" : "One",
                    "route" : "/one"
                },
                {
                    "name" : "Two",
                "route" : "/two"
                },
                {
                    "name" : "Three",
                    "route" : "/three"
                }        
            ]
        },
        {
            "name" : "Pricing",
            "route" : "/pricing"
        }
    ],
    "nav_opt_auth" : [
        {
            "name" : "Home",
            "route" : "/home"
        },
        {
            "name" : "About Us",
            "route" : "/about-us"
        },
        {
            "name" : "Courses",
            "route" : "/courses"
        },
        {
            "name" : "Blog",
            "route" : "/blog"
        },
        {
            "name" : "Contact us",
            "route" : "/cottact-us"
        }
    ]
}